{"top":{"tier":"D","winRate":"46.76%","pickRate":"0.58%","banRate":"5.93%","matches":2040,"skillPriority":["Q","E","W"],"skillOrder":[],"items":{"starting":["1055","2003","1083"],"core":[{"id":"3508","wr":"53.54%"},{"id":"3161","wr":"53.54%"},{"id":"2517","wr":"63.7%"}],"boots":["3009","3158","3047"],"fourth":[{"id":"3031","wr":"57.66%"},{"id":"3094","wr":"61.11%"},{"id":"3072","wr":"62.5%"}],"fifth":[{"id":"3070","wr":null},{"id":"2022","wr":null},{"id":"3057","wr":null}],"sixth":[{"id":"3133","wr":null},{"id":"2055","wr":null},{"id":"3044","wr":null}]},"runes":{"keystone":{"id":"8214","name":"Summon Aery"},"primary":[{"id":"8214","name":"Summon Aery"},{"id":"8229","name":"Arcane Comet"},{"id":"8230","name":"Phase Rush"},{"id":"8224","name":"Axiom Arcanist"},{"id":"8226","name":"Manaflow Band"},{"id":"8275","name":"Nimbus Cloak"},{"id":"8210","name":"Transcendence"},{"id":"8234","name":"Celerity"},{"id":"8233","name":"Absolute Focus"},{"id":"8237","name":"Scorch"},{"id":"8232","name":"Waterwalking"},{"id":"8236","name":"Gathering Storm"}],"secondary":[{"id":"8446","name":"Demolish"},{"id":"8463","name":"Font of Life"},{"id":"8401","name":"Shield Bash"},{"id":"8429","name":"Conditioning"},{"id":"8444","name":"Second Wind"},{"id":"8473","name":"Bone Plating"},{"id":"8451","name":"Overgrowth"},{"id":"8453","name":"Revitalize"},{"id":"8242","name":"Unflinching"}],"shards":["5008","5005","5007","5008","5010","5001","5011","5013","5001"]},"summoners":["Flash","Ignite"],"counters":[{"name":"Irelia","type":"weak"},{"name":"Aatrox","type":"weak"},{"name":"Shen","type":"weak"},{"name":"K'Sante","type":"strong"},{"name":"Garen","type":"strong"},{"name":"Yorick","type":"strong"}]},"mid":{"tier":"D-","winRate":"47.07%","pickRate":"1.1%","banRate":"5.93%","matches":3975,"skillPriority":["Q","E","W"],"skillOrder":[],"items":{"starting":["1055","2003","1083"],"core":[{"id":"3508","wr":"53.78%"},{"id":"3094","wr":"53.78%"},{"id":"2517","wr":"58.43%"}],"boots":["3158","3111","3009"],"fourth":[{"id":"3036","wr":"53.91%"},{"id":"3031","wr":"58.16%"},{"id":"3026","wr":"71.43%"}],"fifth":[{"id":"3072","wr":"63.27%"},{"id":"3070","wr":null},{"id":"2022","wr":null}],"sixth":[{"id":"3057","wr":null},{"id":"3133","wr":null},{"id":"2055","wr":null}]},"runes":{"keystone":{"id":"8214","name":"Summon Aery"},"primary":[{"id":"8214","name":"Summon Aery"},{"id":"8229","name":"Arcane Comet"},{"id":"8230","name":"Phase Rush"},{"id":"8224","name":"Axiom Arcanist"},{"id":"8226","name":"Manaflow Band"},{"id":"8275","name":"Nimbus Cloak"},{"id":"8210","name":"Transcendence"},{"id":"8234","name":"Celerity"},{"id":"8233","name":"Absolute Focus"},{"id":"8237","name":"Scorch"},{"id":"8232","name":"Waterwalking"},{"id":"8236","name":"Gathering Storm"}],"secondary":[{"id":"8446","name":"Demolish"},{"id":"8463","name":"Font of Life"},{"id":"8401","name":"Shield Bash"},{"id":"8429","name":"Conditioning"},{"id":"8444","name":"Second Wind"},{"id":"8473","name":"Bone Plating"},{"id":"8451","name":"Overgrowth"},{"id":"8453","name":"Revitalize"},{"id":"8242","name":"Unflinching"}],"shards":["5008","5005","5007","5008","5010","5001","5011","5013","5001"]},"summoners":["Flash","Ghost"],"counters":[{"name":"Zed","type":"weak"},{"name":"Xerath","type":"weak"},{"name":"Viktor","type":"weak"},{"name":"Lux","type":"strong"},{"name":"Kassadin","type":"strong"},{"name":"Akali","type":"strong"}]},"adc":{"tier":"B-","winRate":"51.28%","pickRate":"9.31%","banRate":"5.93%","matches":34337,"skillPriority":["Q","W","E"],"skillOrder":[],"items":{"starting":["1055","2003","1056"],"core":[{"id":"3508","wr":"57.85%"},{"id":"3161","wr":"57.85%"},{"id":"2517","wr":"59.23%"}],"boots":["3158","3009","3047"],"fourth":[{"id":"3031","wr":"56.74%"},{"id":"3094","wr":"59.1%"},{"id":"3036","wr":"63.12%"}],"fifth":[{"id":"3026","wr":"62.55%"},{"id":"3070","wr":null},{"id":"2022","wr":null}],"sixth":[{"id":"3057","wr":null},{"id":"3133","wr":null},{"id":"2055","wr":null}]},"runes":{"keystone":{"id":"8214","name":"Summon Aery"},"primary":[{"id":"8214","name":"Summon Aery"},{"id":"8229","name":"Arcane Comet"},{"id":"8230","name":"Phase Rush"},{"id":"8224","name":"Axiom Arcanist"},{"id":"8226","name":"Manaflow Band"},{"id":"8275","name":"Nimbus Cloak"},{"id":"8210","name":"Transcendence"},{"id":"8234","name":"Celerity"},{"id":"8233","name":"Absolute Focus"},{"id":"8237","name":"Scorch"},{"id":"8232","name":"Waterwalking"},{"id":"8236","name":"Gathering Storm"}],"secondary":[{"id":"8306","name":"Hextech Flashtraption"},{"id":"8304","name":"Magical Footwear"},{"id":"8321","name":"Cash Back"},{"id":"8313","name":"Triple Tonic"},{"id":"8352","name":"Time Warp Tonic"},{"id":"8345","name":"Biscuit Delivery"},{"id":"8347","name":"Cosmic Insight"},{"id":"8410","name":"Approach Velocity"},{"id":"8316","name":"Jack Of All Trades"}],"shards":["5008","5005","5007","5008","5010","5001","5011","5013","5001"]},"summoners":["Cleanse","Flash"],"counters":[{"name":"Senna","type":"weak"},{"name":"Brand","type":"weak"},{"name":"Kog'Maw","type":"weak"},{"name":"Yunara","type":"strong"},{"name":"Vayne","type":"strong"},{"name":"Varus","type":"strong"}]},"support":{"tier":null,"winRate":"30.91%","pickRate":"0.02%","banRate":"5.93%","matches":55,"skillPriority":["Q","W","E"],"skillOrder":[],"items":{"starting":["2003","2031","1083"],"core":[{"id":"3865","wr":null},{"id":"2022","wr":null},{"id":"3133","wr":null}],"boots":["3158","3009","3020"],"fourth":[{"id":"3364","wr":null},{"id":"3057","wr":null},{"id":"2055","wr":null}],"fifth":[{"id":"3070","wr":null},{"id":"3134","wr":null},{"id":"3145","wr":null}],"sixth":[{"id":"3802","wr":null},{"id":"3508","wr":null},{"id":"2508","wr":null}]},"runes":{"keystone":{"id":"8005","name":"Press the Attack"},"primary":[{"id":"8005","name":"Press the Attack"},{"id":"8008","name":"Lethal Tempo"},{"id":"8021","name":"Fleet Footwork"},{"id":"8010","name":"Conqueror"},{"id":"9101","name":"Absorb Life"},{"id":"9111","name":"Triumph"},{"id":"8009","name":"Presence of Mind"},{"id":"9104","name":"Legend: Alacrity"},{"id":"9105","name":"Legend: Haste"},{"id":"9103","name":"Legend: Bloodline"},{"id":"8014","name":"Coup de Grace"},{"id":"8017","name":"Cut Down"},{"id":"8299","name":"Last Stand"}],"secondary":[{"id":"8126","name":"Cheap Shot"},{"id":"8139","name":"Taste of Blood"},{"id":"8143","name":"Sudden Impact"},{"id":"8137","name":"Sixth Sense"},{"id":"8140","name":"Grisly Mementos"},{"id":"8141","name":"Deep Ward"},{"id":"8135","name":"Treasure Hunter"},{"id":"8105","name":"Relentless Hunter"},{"id":"8106","name":"Ultimate Hunter"},{"id":"8224","name":"Axiom Arcanist"},{"id":"8226","name":"Manaflow Band"},{"id":"8275","name":"Nimbus Cloak"},{"id":"8210","name":"Transcendence"},{"id":"8234","name":"Celerity"},{"id":"8233","name":"Absolute Focus"},{"id":"8237","name":"Scorch"},{"id":"8232","name":"Waterwalking"},{"id":"8236","name":"Gathering Storm"},{"id":"8446","name":"Demolish"},{"id":"8463","name":"Font of Life"},{"id":"8401","name":"Shield Bash"},{"id":"8429","name":"Conditioning"},{"id":"8444","name":"Second Wind"},{"id":"8473","name":"Bone Plating"},{"id":"8451","name":"Overgrowth"},{"id":"8453","name":"Revitalize"},{"id":"8242","name":"Unflinching"},{"id":"8306","name":"Hextech Flashtraption"},{"id":"8304","name":"Magical Footwear"},{"id":"8321","name":"Cash Back"},{"id":"8313","name":"Triple Tonic"},{"id":"8352","name":"Time Warp Tonic"},{"id":"8345","name":"Biscuit Delivery"},{"id":"8347","name":"Cosmic Insight"},{"id":"8410","name":"Approach Velocity"},{"id":"8316","name":"Jack Of All Trades"},{"id":"9101","name":"Absorb Life"},{"id":"9111","name":"Triumph"},{"id":"8009","name":"Presence of Mind"},{"id":"9104","name":"Legend: Alacrity"},{"id":"9105","name":"Legend: Haste"},{"id":"9103","name":"Legend: Bloodline"},{"id":"8014","name":"Coup de Grace"},{"id":"8017","name":"Cut Down"},{"id":"8299","name":"Last Stand"},{"id":"8126","name":"Cheap Shot"},{"id":"8139","name":"Taste of Blood"},{"id":"8143","name":"Sudden Impact"},{"id":"8137","name":"Sixth Sense"},{"id":"8140","name":"Grisly Mementos"},{"id":"8141","name":"Deep Ward"},{"id":"8135","name":"Treasure Hunter"},{"id":"8105","name":"Relentless Hunter"},{"id":"8106","name":"Ultimate Hunter"},{"id":"8224","name":"Axiom Arcanist"},{"id":"8226","name":"Manaflow Band"},{"id":"8275","name":"Nimbus Cloak"},{"id":"8210","name":"Transcendence"},{"id":"8234","name":"Celerity"},{"id":"8233","name":"Absolute Focus"},{"id":"8237","name":"Scorch"},{"id":"8232","name":"Waterwalking"},{"id":"8236","name":"Gathering Storm"},{"id":"8446","name":"Demolish"},{"id":"8463","name":"Font of Life"},{"id":"8401","name":"Shield Bash"},{"id":"8429","name":"Conditioning"},{"id":"8444","name":"Second Wind"},{"id":"8473","name":"Bone Plating"},{"id":"8451","name":"Overgrowth"},{"id":"8453","name":"Revitalize"},{"id":"8242","name":"Unflinching"},{"id":"8306","name":"Hextech Flashtraption"},{"id":"8304","name":"Magical Footwear"},{"id":"8321","name":"Cash Back"},{"id":"8313","name":"Triple Tonic"},{"id":"8352","name":"Time Warp Tonic"},{"id":"8345","name":"Biscuit Delivery"},{"id":"8347","name":"Cosmic Insight"},{"id":"8410","name":"Approach Velocity"},{"id":"8316","name":"Jack Of All Trades"}],"shards":["5008","5005","5007","5008","5010","5001","5011","5013","5001"]},"summoners":["Flash","Barrier"],"counters":[]}}